git_commits_graph/__init__.py
git_commits_graph/config.py
git_commits_graph/main.py
git_commits_graph/plotters.py
git_commits_graph-0.2.2.dist-info/METADATA
git_commits_graph-0.2.2.dist-info/WHEEL
git_commits_graph-0.2.2.dist-info/entry_points.txt
git_commits_graph-0.2.2.dist-info/RECORD
