Metadata-Version: 2.1
Name: git-commits-graph
Version: 0.2.2
Summary: Display graph of changes in number of lines in project or changed lines
License: MIT
Author: Krystian Safjan
Author-email: ksafjan@gmail.com
Requires-Python: >=3.8,<4.0
Classifier: License :: OSI Approved :: MIT License
Classifier: Programming Language :: Python :: 3
Classifier: Programming Language :: Python :: 3.8
Classifier: Programming Language :: Python :: 3.9
Classifier: Programming Language :: Python :: 3.10
Classifier: Programming Language :: Python :: 3.11
Requires-Dist: GitPython (>=3.1.27,<4.0.0)
Requires-Dist: click (>=8.1.3,<9.0.0)
Requires-Dist: matplotlib (>=3.7.1,<4.0.0)
Requires-Dist: pandas (>=1.5.3,<2.0.0)
Requires-Dist: plotly (>=5.14.0,<6.0.0)
Requires-Dist: tqdm (>=4.65.0,<5.0.0)
